torchregularize/__init__.py
torchregularize/dropblock.py
torchregularize/shakedrop.py
torchregularize/stochastic_depth.py
torchregularize-0.1.0.dist-info/METADATA
torchregularize-0.1.0.dist-info/WHEEL
torchregularize-0.1.0.dist-info/top_level.txt
torchregularize-0.1.0.dist-info/RECORD
